kakariki/__init__.py
kakariki-0.0.1.dist-info/licenses/LICENSE
kakariki-0.0.1.dist-info/METADATA
kakariki-0.0.1.dist-info/WHEEL
kakariki-0.0.1.dist-info/top_level.txt
kakariki-0.0.1.dist-info/RECORD
